numerary/__init__.py
numerary/_version.py
numerary/bt.py
numerary/protocol.py
numerary/py.typed
numerary/types.py
numerary-0.4.4.dist-info/LICENSE
numerary-0.4.4.dist-info/METADATA
numerary-0.4.4.dist-info/WHEEL
numerary-0.4.4.dist-info/top_level.txt
numerary-0.4.4.dist-info/RECORD
