Metadata-Version: 2.1
Name: numerary
Version: 0.4.4
Summary: Python hacks for type-checking numbers
Home-page: https://posita.github.io/numerary/
Author: Matt Bogosian
Author-email: matt@bogosian.net
License: MIT License
Project-URL: Source Repository, https://github.com/posita/numerary/
Classifier: Topic :: Education
Classifier: Topic :: Scientific/Engineering :: Mathematics
Classifier: Topic :: Software Development :: Libraries :: Python Modules
Classifier: Typing :: Typed
Classifier: Development Status :: 4 - Beta
Classifier: Intended Audience :: Developers
Classifier: Intended Audience :: Education
Classifier: Intended Audience :: Science/Research
Classifier: License :: OSI Approved :: MIT License
Classifier: Operating System :: OS Independent
Classifier: Programming Language :: Python
Classifier: Programming Language :: Python :: 3.8
Classifier: Programming Language :: Python :: 3.9
Classifier: Programming Language :: Python :: 3.10
Classifier: Programming Language :: Python :: 3.11
Classifier: Programming Language :: Python :: Implementation :: CPython
Classifier: Programming Language :: Python :: Implementation :: PyPy
Requires-Python: >=3.8
License-File: LICENSE
Requires-Dist: beartype (~=0.15)
Provides-Extra: dev
Requires-Dist: pre-commit ; extra == 'dev'
Requires-Dist: numpy (~=1.25) ; extra == 'dev'
Requires-Dist: sympy (~=1.9) ; extra == 'dev'
Requires-Dist: tox (~=4.0) ; extra == 'dev'
Requires-Dist: versioningit (~=2.0) ; extra == 'dev'
